weatherchart/__init__.py
weatherchart/weatherchart.py
weatherchart-1.0.6.dist-info/LICENSE
weatherchart-1.0.6.dist-info/WHEEL
weatherchart-1.0.6.dist-info/METADATA
weatherchart-1.0.6.dist-info/RECORD
